minitonu/__init__.py
minitonu/core.py
minitonu/neural.py
minitonu/tests.py
minitonu-0.1.0.dist-info/METADATA
minitonu-0.1.0.dist-info/WHEEL
minitonu-0.1.0.dist-info/top_level.txt
minitonu-0.1.0.dist-info/RECORD
