Metadata-Version: 2.4
Name: minitonu
Version: 0.1.0
Summary: Microbiblioteca sin dependencias inspirada en torch y numpy.
Author-email: Luis Fernando Montaño <tucorreo@example.com>
License: MIT
Project-URL: Homepage, https://pypi.org/project/minitonu/
Keywords: tensor,neuralnet,educational,minimal,python-puro
Classifier: Programming Language :: Python :: 3
Classifier: License :: OSI Approved :: MIT License
Classifier: Operating System :: OS Independent
Requires-Python: >=3.6
